tps_agent/__init__.py
tps_agent/agent.py
tps_agent/config.py
tps_agent/decorators.py
tps_agent/models.py
tps_agent/storage.py
tps_agent/strategy_agent.py
tps_agent/strategy_decorators.py
tps_agent/transmission.py
tps_agent/grafana/__init__.py
tps_agent/grafana/grafana_integration.py
tps_agent/grafana/prometheus_exporter.py
tps_agent/strategies/__init__.py
tps_agent/strategies/base.py
tps_agent/strategies/collector_strategy.py
tps_agent/strategies/hybrid_strategy.py
tps_agent/strategies/postgresql_strategy.py
tps_agent/strategies/prometheus_strategy.py
tps_agent-2.2.1.dist-info/licenses/LICENSE
tps_agent-2.2.1.dist-info/METADATA
tps_agent-2.2.1.dist-info/WHEEL
tps_agent-2.2.1.dist-info/entry_points.txt
tps_agent-2.2.1.dist-info/top_level.txt
tps_agent-2.2.1.dist-info/RECORD
