Metadata-Version: 2.4
Name: tps-agent
Version: 2.2.1
Summary: Comprehensive TPS monitoring and throttling library with database-driven controls
Home-page: https://github.com/tps-agent/tps-agent
Author: Earlypay
Author-email: TPS Agent Contributors <contact@tps-agent.dev>
License-Expression: MIT
Project-URL: Homepage, https://github.com/tps-agent/tps-agent
Project-URL: Repository, https://github.com/tps-agent/tps-agent
Project-URL: Documentation, https://tps-agent.readthedocs.io
Project-URL: Changelog, https://github.com/tps-agent/tps-agent/blob/main/CHANGELOG.md
Classifier: Development Status :: 4 - Beta
Classifier: Intended Audience :: Developers
Classifier: Operating System :: OS Independent
Classifier: Programming Language :: Python :: 3
Classifier: Programming Language :: Python :: 3.8
Classifier: Programming Language :: Python :: 3.9
Classifier: Programming Language :: Python :: 3.10
Classifier: Programming Language :: Python :: 3.11
Classifier: Programming Language :: Python :: 3.12
Classifier: Topic :: System :: Monitoring
Classifier: Topic :: Software Development :: Libraries :: Python Modules
Classifier: Topic :: Internet :: WWW/HTTP :: HTTP Servers
Classifier: Topic :: Database
Requires-Python: >=3.8
License-File: LICENSE
Requires-Dist: requests<3.0.0,>=2.25.0
Provides-Extra: postgresql
Requires-Dist: psycopg2-binary<3.0.0,>=2.9.0; extra == "postgresql"
Provides-Extra: prometheus
Requires-Dist: prometheus_client<1.0.0,>=0.16.0; extra == "prometheus"
Provides-Extra: all
Requires-Dist: psycopg2-binary<3.0.0,>=2.9.0; extra == "all"
Requires-Dist: prometheus_client<1.0.0,>=0.16.0; extra == "all"
Provides-Extra: dev
Requires-Dist: pytest>=6.0; extra == "dev"
Requires-Dist: pytest-cov>=2.0; extra == "dev"
Requires-Dist: black>=21.0; extra == "dev"
Requires-Dist: isort>=5.0; extra == "dev"
Requires-Dist: flake8>=3.8; extra == "dev"
Requires-Dist: psycopg2-binary<3.0.0,>=2.9.0; extra == "dev"
Requires-Dist: prometheus_client<1.0.0,>=0.16.0; extra == "dev"
Dynamic: author
Dynamic: home-page
Dynamic: license-file
Dynamic: requires-python
